{
  "_comment": "VEP1445 Runtime Configuration Example",
  "_note": "This file is auto-generated at runtime. You can pre-configure interfaces and profiles here.",
  
  "interfaces": {
    "eno2": {
      "name": "eno2",
      "mac_address": "00:11:22:33:44:55",
      "ip_address": "24.1.6.142",
      "subnet_mask": "255.255.255.224",
      "gateway": "24.1.6.129",
      "ipv6_address": null,
      "vlan_id": null,
      "enabled": true,
      "use_dhcp": true,
      "interface_type": "copper"
    },
    "eno3": {
      "name": "eno3",
      "mac_address": "00:11:22:33:44:66",
      "ip_address": "24.1.1.139",
      "subnet_mask": "255.255.255.224",
      "gateway": "24.1.1.129",
      "ipv6_address": null,
      "vlan_id": null,
      "enabled": true,
      "use_dhcp": true,
      "interface_type": "copper"
    }
  },
  
  "traffic_profiles": {
    "UDP_Bulk_Test": {
      "name": "UDP_Bulk_Test",
      "src_interface": "eno2",
      "dst_interface": "eno3",
      "dst_ip": "24.1.1.139",
      "dst_port": 9999,
      "protocol": "udp",
      "bandwidth_mbps": 100,
      "packet_size": 1400,
      "duration": 0,
      "enabled": false,
      "imix_enabled": false,
      "rfc2544_throughput_test": false,
      "rfc2544_latency_test": false,
      "rfc2544_frame_loss_test": false,
      "rfc2544_back_to_back_test": false
    },
    "TCP_Connection_Test": {
      "name": "TCP_Connection_Test",
      "src_interface": "eno2",
      "dst_interface": "eno3",
      "dst_ip": "24.1.1.139",
      "dst_port": 80,
      "protocol": "tcp",
      "connections_per_sec": 100,
      "duration": 0,
      "enabled": false
    }
  },
  
  "system": {
    "auto_load_profiles": true,
    "neighbor_discovery_interval": 10,
    "stats_update_interval": 1
  }
}
